Workbook

Sheet 寶成年增率
A1: 年度 | B1: 季度 | C1: 年增率/單季稅後淨利成長率 | D1: 年增率/近4季稅後淨利成長率 | E1: ROE% | F1: ROA% | G1: 年度營收 | H1: 年度稅後淨利 | I1: 淨利率
A2: 2025 | B2: Q1 | C2: -22.6 | D2: 8.23 | E2: 2.23 | F2: 1.41 | G2: 67030257 | H2: 5036353 | I2: =H2/G2 -> 0.075135517
A3: 2024 | B3: Q4 | C3: 44.06 | D3: 46.72 | E3: 1.68 | F3: 1.06 | G3: 68397788 | H3: 3762504 | I3: =H3/G3 -> 0.055009147
A4: 2024 | B4: Q3 | C4: 16.51 | D4: 103.43 | E4: 3.69 | F4: 2.3 | G4: 66803825 | H4: 8145754 | I4: =H4/G4 -> 0.12193544
A5: 2024 | B5: Q2 | C5: 19.97 | D5: 90.1 | E5: 2.31 | F5: 1.44 | G5: 65327340 | H5: 5020804 | I5: =H5/G5 -> 0.076856091
A6: 2024 | B6: Q1 | C6: 197.8 | D6: 56.1 | E6: 3.11 | F6: 1.93 | G6: 63288874 | H6: 6506840 | I6: =H6/G6 -> 0.10281175
A7: 2023 | B7: Q4 | C7: -208.52 | D7: -5.42 | E7: 1.3 | F7: 0.78 | G7: 60875744 | H7: 2611804 | I7: =H7/G7 -> 0.042903853
A8: 2023 | B8: Q3 | C8: -2.25 | D8: -47.54 | E8: 3.58 | F8: 2.11 | G8: 58295948 | H8: 6991563 | I8: =H8/G8 -> 0.11993223
A9: 2023 | B9: Q2 | C9: -31.07 | D9: -27.33 | E9: 2.2 | F9: 1.29 | G9: 63095229 | H9: 4185131 | I9: =H9/G9 -> 0.066330388
A10: 2023 | B10: Q1 | C10: -64.02 | D10: -10.65 | E10: 1.18 | F10: 0.67 | G10: 64366793 | H10: 2184983 | I10: =H10/G10 -> 0.033945811
A11: 2022 | B11: Q4 | C11: -251.54 | D11: 1.72 | E11: -1.45 | F11: -0.75 | G11: 62919855 | H11: -2406712 | I11: =H11/G11 -> -0.038250438
A12: 2022 | B12: Q3 | C12: 357.63 | D12: 23.2 | E12: 4.94 | F12: 2.28 | G12: 68975710 | H12: 7152181 | I12: =H12/G12 -> 0.1036913
A13: 2022 | B13: Q2 | C13: 13.97 | D13: -18.31 | E13: 3.73 | F13: 1.85 | G13: 68337874 | H13: 6071210 | I13: =H13/G13 -> 0.088841072
... A22: 2020 | B22: Q1 | C22: -98.15 | D22: -20.12 | E22: 0.05 | F22: 0.02 | G22: 59448420 | H22: 82208 | I22: =H22/G22 -> 0.0013828458

Sheet 寶成ROE.ROA
A1: 年度 | B1: 年度ROE% | C1: 年度ROA% | D1: 年度淨利率
A2: 2025 | B2: 2.23 | C2: 1.41 | D2: =SUM(寶成年增率!I2) -> 0.075135517
A3: 2024 | B3: 10.8 | C3: 6.73 | D3: =SUM(寶成年增率!I3:I6)/4 -> 0.089153108
A4: 2023 | B4: 8.27 | C4: 4.85 | D4: =SUM(寶成年增率!I7:I10)/4 -> 0.06577807
A5: 2022 | B5: 10.31 | C5: 5.08 | D5: =SUM(寶成年增率!I11:I14)/4 -> 0.061141416
A6: 2021 | B6: 8.43 | C6: 4.58 | D6: =SUM(寶成年增率!I15:I118)/4 -> 0.080444379
A7: 2020 | B7: 2.03 | C7: 1.09 | D7: =SUM(寶成年增率!I19:I22)/4 -> 0.015916339

Sheet 豐泰企業年增率
A1: 年度 | B1: 季度 | C1: 年增率/單季稅後淨利成長率 | D1: 年增率/近4季稅後淨利成長率 | E1: ROE% | F1: ROA% | G1: 年度營收 | H1: 年度稅後淨利 | I1: 淨利率
A2: 2025 | B2: Q1 | C2: -10.7 | D2: 0.0326 | E2: 4.06 | F2: 2.2 | G2: 20722823 | H2: 1196287 | I2: =H2/G2 -> 0.057727994
A3: 2024 | B3: Q4 | C3: 18.44 | D3: 0.1505 | E3: 6.23 | F3: 3.2 | G3: 21885271 | H3: 1701699 | I3: =H3/G3 -> 0.077755446
A4: 2024 | B4: Q3 | C4: -16 | D4: 0.0336 | E4: 6.04 | F4: 2.92 | G4: 22719052 | H4: 1530188 | I4: =H4/G4 -> 0.067352634
A5: 2024 | B5: Q2 | C5: 27.26 | D5: -0.0927 | E5: 6.51 | F5: 3.24 | G5: 22266696 | H5: 1694050 | I5: =H5/G5 -> 0.07607999
A6: 2024 | B6: Q1 | C6: 56.41 | D6: -0.2953 | E6: 5.13 | F6: 2.62 | G6: 20616451 | H6: 1339620 | I6: =H6/G6 -> 0.064978206
A7: 2023 | B7: Q4 | C7: -20.01 | D7: -0.4423 | E7: 5.77 | F7: 2.79 | G7: 22535192 | H7: 1436713 | I7: =H7/G7 -> 0.063754194
A8: 2023 | B8: Q3 | C8: -38.27 | D8: -0.4046 | E8: 7.77 | F8: 3.54 | G8: 23072896 | H8: 1821633 | I8: =H8/G8 -> 0.078951208
A9: 2023 | B9: Q2 | C9: -52.62 | D9: 0.0683 | E9: 5.4 | F9: 2.65 | G9: 20656426 | H9: 1331123 | I9: =H9/G9 -> 0.064441109
A10: 2023 | B10: Q1 | C10: -61.2 | D10: 0.5186 | E10: 3.17 | F10: 1.69 | G10: 19502750 | H10: 856468 | I10: =H10/G10 -> 0.043915243
A11: 2022 | B11: Q4 | C11: 0.77 | D11: 0.8917 | E11: 6.79 | F11: 3.43 | G11: 22863424 | H11: 1796157 | I11: =H11/G11 -> 0.07856028
A12: 2022 | B12: Q3 | C12: -1059.27 | D12: 1.0524 | E12: 12.34 | F12: 5.7 | G12: 25881159 | H12: 2951136 | I12: =H12/G12 -> 0.11402642
A13: 2022 | B13: Q2 | C13: 51.22 | D13: -0.0401 | E13: 12.77 | F13: 5.62 | G13: 24763347 | H13: 2809580 | I13: =H13/G13 -> 0.1134572
... A22: 2020 | B22: Q1 | C22: -0.1361 | D22: 0.0182 | E22: 7.33 | F22: 3.35 | G22: 18120215 | H22: 1407013 | I22: =H22/G22 -> 0.077648803

Sheet 豐泰ROE.ROA
A1: 年度 | B1: 年度ROE% | C1: 年度ROA% | D1: 年度淨利率
A2: 2025 | B2: 4.06 | C2: 2.2 | D2: =SUM(豐泰企業年增率!I2) -> 0.057727994
A3: 2024 | B3: 23.92 | C3: 11.97 | D3: =SUM(豐泰企業年增率!I3:I6)/4 -> 0.071541569
A4: 2023 | B4: 22.11 | C4: 10.67 | D4: =SUM(豐泰企業年增率!I7:I10)/4 -> 0.062765438
A5: 2022 | B5: 42.4 | C5: 19.32 | D5: =SUM(豐泰企業年增率!I11:I14)/4 -> 0.10115264
A6: 2021 | B6: 25.77 | C6: 11.76 | D6: =SUM(豐泰企業年增率!I15:I118)/4 -> 0.14583758
A7: 2020 | B7: 29.95 | C7: 13.54 | D7: =SUM(豐泰企業年增率!I19:I22)/4 -> 0.080921318

Sheet 鈺齊年增率
A1: 年度 | B1: 季度 | C1: 年增率/單季稅後淨利成長率 | D1: 年增率/近4季稅後淨利成長率 | E1: ROE% | F1: ROA% | G1: 年度營收 | H1: 年度稅後淨利 | I1: 淨利率
A2: 2025 | B2: Q1 | C2: -11.16 | D2: 2.9 | E2: 1.78 | F2: 1.14 | G2: 3667587 | H2: 250567 | I2: =H2/G2 -> 0.068319306
A3: 2024 | B3: Q4 | C3: 826.74 | D3: -8.23 | E3: 4.31 | F3: 2.79 | G3: 4388170 | H3: 583528 | I3: =H3/G3 -> 0.13297753
A4: 2024 | B4: Q3 | C4: -69.96 | D4: -58.09 | E4: 0.79 | F4: 0.51 | G4: 3598903 | H4: 101675 | I4: =H4/G4 -> 0.028251664
A5: 2024 | B5: Q2 | C5: -34.53 | D5: -63.58 | E5: 3.22 | F5: 2.1 | G5: 3965185 | H5: 406613 | I5: =H5/G5 -> 0.10254578
A6: 2024 | B6: Q1 | C6: -40.56 | D6: -60.79 | E6: 2.28 | F6: 1.49 | G6: 2659213 | H6: 282030 | I6: =H6/G6 -> 0.10605769
A7: 2023 | B7: Q4 | C7: -89.54 | D7: -55.91 | E7: 0.49 | F7: 0.33 | G7: 3680586 | H7: 62966 | I7: =H7/G7 -> 0.017107602
A8: 2023 | B8: Q3 | C8: -73.88 | D8: -36.01 | E8: 2.63 | F8: 1.69 | G8: 3542788 | H8: 338469 | I8: =H8/G8 -> 0.095537469
A9: 2023 | B9: Q2 | C9: -34.92 | D9: 34.39 | E9: 5.07 | F9: 2.97 | G9: 4616288 | H9: 621079 | I9: =H9/G9 -> 0.13454078
A10: 2023 | B10: Q1 | C10: -12.68 | D10: 137.17 | E10: 3.86 | F10: 2.14 | G10: 5053564 | H10: 474464 | I10: =H10/G10 -> 0.093887007
A11: 2022 | B11: Q4 | C11: 55.07 | D11: 186.62 | E11: 4.82 | F11: 2.58 | G11: 6216051 | H11: 602000 | I11: =H11/G11 -> 0.096846052
A12: 2022 | B12: Q3 | C12: 279.39 | D12: 223.8 | E12: 11.25 | F12: 5.62 | G12: 7238216 | H12: 1295883 | I12: =H12/G12 -> 0.17903348
A13: 2022 | B13: Q2 | C13: 636.83 | D13: 169.87 | E13: 9.54 | F13: 4.52 | G13: 6199851 | H13: 954320 | I13: =H13/G13 -> 0.15392628
... A22: 2020 | B22: Q1 | C22: 72.69 | D22: 68.83 | E22: 4.2 | F22: 2.72 | G22: 2772864 | H22: 353620 | I22: =H22/G22 -> 0.12752879

Sheet 鈺齊ROE.ROA
A1: 年度 | B1: 年度ROE% | C1: 年度ROA% | D1: 年度淨利率
A2: 2025 | B2: 1.78 | C2: 1.14 | D2: =SUM(鈺齊年增率!I2) -> 0.068319306
A3: 2024 | B3: 10.59 | C3: 6.89 | D3: =SUM(鈺齊年增率!I3:I6)/4 -> 0.092458168
A4: 2023 | B4: 12.06 | C4: 7.12 | D4: =SUM(鈺齊年增率!I7:I10)/4 -> 0.085268215
A5: 2022 | B5: 31.51 | C5: 15.61 | D5: =SUM(鈺齊年增率!I11:I14)/4 -> 0.1374566
A6: 2021 | B6: 13.61 | C6: 7.36 | D6: =SUM(鈺齊年增率!I15:I118)/4 -> 0.15512591
A7: 2020 | B7: 10.75 | C7: 6.7 | D7: =SUM(鈺齊年增率!I19:I22)/4 -> 0.079860091

Sheet 百和年增率
A1: 年度 | B1: 季度 | C1: 年增率/單季稅後淨利成長率 | D1: 年增率/近4季稅後淨利成長率 | E1: ROE% | F1: ROA% | G1: 年度營收 | H1: 年度稅後淨利 | I1: 淨利率
A2: 2025 | B2: Q1 | C2: 53.93 | D2: 209.62 | E2: 3.43 | F2: 1.69 | G2: 4250077 | H2: 564274 | I2: =H2/G2 -> 0.13276795
A3: 2024 | B3: Q4 | C3: 1184.56 | D3: 476.65 | E3: 1.83 | F3: 0.9 | G3: 3862088 | H3: 296656 | I3: =H3/G3 -> 0.076812336
A4: 2024 | B4: Q3 | C4: 112.3 | D4: 342.95 | E4: 3.33 | F4: 1.59 | G4: 4319727 | H4: 524954 | I4: =H4/G4 -> 0.12152481
A5: 2024 | B5: Q2 | C5: -821.96 | D5: 107.07 | E5: 2.69 | F5: 1.24 | G5: 3721560 | H5: 410267 | I5: =H5/G5 -> 0.1102406
A6: 2024 | B6: Q1 | C6: 475.86 | D6: -56 | E6: 2.54 | F6: 1.13 | G6: 3555193 | H6: 366574 | I6: =H6/G6 -> 0.10310945
A7: 2023 | B7: Q4 | C7: -48.68 | D7: -84.5 | E7: 0.16 | F7: 0.07 | G7: 3157143 | H7: 23094 | I7: =H7/G7 -> 0.0073148413
A8: 2023 | B8: Q3 | C8: -45.52 | D8: -86.82 | E8: 1.78 | F8: 0.76 | G8: 3576684 | H8: 247272 | I8: =H8/G8 -> 0.069134427
A9: 2023 | B9: Q2 | C9: -107.52 | D9: -77.34 | E9: -0.4 | F9: -0.18 | G9: 2707641 | H9: -56827 | I9: =H9/G9 -> -0.020987642
A10: 2023 | B10: Q1 | C10: -88.08 | D10: -45.72 | E10: 0.44 | F10: 0.2 | G10: 3003735 | H10: 63657 | I10: =H10/G10 -> 0.021192615
A11: 2022 | B11: Q4 | C11: -91.43 | D11: -32.91 | E11: 0.31 | F11: 0.14 | G11: 2963038 | H11: 45002 | I11: =H11/G11 -> 0.01518779
A12: 2022 | B12: Q3 | C12: 8.87 | D12: -13.3 | E12: 3.17 | F12: 1.38 | G12: 4006920 | H12: 453890 | I12: =H12/G12 -> 0.11327653
A13: 2022 | B13: Q2 | C13: -20.71 | D13: -14.11 | E13: 5.58 | F13: 2.43 | G13: 5035531 | H13: 755976 | I13: =H13/G13 -> 0.15012836
... A22: 2020 | B22: Q1 | C22: 34.21 | D22: 17.86 | E22: 5.52 | F22: 2.24 | G22: 4597397 | H22: 632328 | I22: =H22/G22 -> 0.13754044

Sheet 百和ROE.ROA
A1: 年度 | B1: 年度ROE% | C1: 年度ROA% | D1: 年度淨利率
A2: 2025 | B2: 3.43 | C2: 1.69 | D2: =SUM(百和年增率!I2) -> 0.13276795
A3: 2024 | B3: 10.39 | C3: 4.86 | D3: =SUM(百和年增率!I3:I6)/4 -> 0.1029218
A4: 2023 | B4: 1.98 | C4: 0.85 | D4: =SUM(百和年增率!I7:I10)/4 -> 0.01916356
A5: 2022 | B5: 13.05 | C5: 5.75 | D5: =SUM(百和年增率!I11:I14)/4 -> 0.10094512
A6: 2021 | B6: 20.93 | C6: 8.61 | D6: =SUM(百和年增率!I15:I118)/4 -> 0.26344002
A7: 2020 | B7: 15.45 | C7: 6.16 | D7: =SUM(百和年增率!I19:I22)/4 -> 0.12077925

Sheet 寶成2025Q1資負
A1: 類別 | B1: 項目名稱 | C1: 會計科目 | D1: 時間 | E1: 金額
A2: 資產 | B2: 流動資產 | C2: 現金及約當現金 | D2: 45747 | E2: 29735785
A3: 資產 | B3: 流動資產 | C3: 透過損益按公允價值衡量之金融資產－流動 | D3: 45747 | E3: 1555026
A4: 資產 | B4: 流動資產 | C4: 透過其他綜合損益按公允價值衡量之金融資產－流動 | D4: 45747 | E4: 24306639
A5: 資產 | B5: 流動資產 | C5: 按攤銷後成本衡量之金融資產－流動 | D5: 45747 | E5: 12727955
A6: 資產 | B6: 流動資產 | C6: 應收票據 | D6: 45747 | E6: 481
A7: 資產 | B7: 流動資產 | C7: 應收帳款 | D7: 45747 | E7: 31550519
A8: 資產 | B8: 流動資產 | C8: 其他應收款 | D8: 45747 | E8: 8804743
A9: 資產 | B9: 流動資產 | C9: 本期所得稅資產 | D9: 45747 | E9: 1097718
A10: 資產 | B10: 流動資產 | C10: 存貨－製造及零批業 | D10: 45747 | E10: 49813833
A11: 資產 | B11: 流動資產 | C11: 存貨－建設業 | D11: 45747 | E11: 3912937
A12: 資產 | B12: 流動資產 | C12: 其他流動資產 | D12: 45747 | E12: 12550557
A13: 資產 | B13: 非流動資產 | C13: 透過損益按公允價值衡量之金融資產－非流動 | D13: 45747 | E13: 2434435
... A41: 權益 | B41: 資本公積 | C41: 資本公積 | D41: 45747 | E41: 4517841
A42: 權益 | B42: 未分類 | C42: 保留盈餘 | D42: 45747
A43: 權益 | B43: 保留盈餘 | C43: 法定盈餘公積 | D43: 45747 | E43: 20344110
A44: 權益 | B44: 保留盈餘 | C44: 特別盈餘公積 | D44: 45747 | E44: 55117885
A45: 權益 | B45: 保留盈餘 | C45: 未分配盈餘 | D45: 45747 | E45: 42322723
A46: 權益 | B46: 其他權益 | C46: 其他權益 | D46: 45747 | E46: -9732447
A47: 權益 | B47: 非控制權益 | C47: 非控制權益 | D47: 45747 | E47: 83533204

Sheet 寶成2025Q1損益
A1: 項目名稱 | B1: 會計科目 | C1: 時間 | D1: 金額
A2: 銷貨收入 | B2: 銷貨收入 | C2: 45747 | D2: 67030257
A3: 銷貨成本 | B3: 銷貨成本 | C3: 45747 | D3: 51418086
A4: 營業費用 | B4: 推銷費用 | C4: 45747 | D4: 6809244
A5: 營業費用 | B5: 管理費用 | C5: 45747 | D5: 4637765
A6: 營業費用 | B6: 研究發展費用 | C6: 45747 | D6: 1190804
A7: 營業費用 | B7: 營業費用合計 | C7: 45747 | D7: 12637813
A8: 營業外費用 | B8: 利息收入 | C8: 45747 | D8: 471390
A9: 營業外費用 | B9: 其他收入 | C9: 45747 | D9: 601169
A10: 營業外費用 | B10: 其他利益及（損失） | C10: 45747 | D10: 195219
A11: 營業外費用 | B11: 財務成本 | C11: 45747 | D11: -645598
A12: 營業外費用 | B12: 採用權益法認列之關聯企業及合資利益之份額企業及合資利益之份額 | C12: 45747 | D12: 2657410
A13: 所得稅費用 | B13: 所得稅費用 | C13: 45747 | D13: 1217595

Sheet 寶成2025Q1現流
A1: 項目名稱 | B1: 會計科目 | C1: 時間 | D1: 金額
A2: 營業活動 | B2: 本期稅前淨利 | C2: 45747 | D2: 6253948
A3: 營業活動 | B3: 折舊費用 | C3: 45747 | D3: 3018342
A4: 營業活動 | B4: 攤銷費用 | C4: 45747 | D4: 41668
A5: 營業活動 | B5: 預期信用減損（迴轉利益）損失 | C5: 45747 | D5: -9770
A6: 營業活動 | B6: 透過損益按公允價值衡量之金融商品淨利益 | C6: 45747 | D6: -66693
A7: 營業活動 | B7: 財務成本 | C7: 45747 | D7: 645598
A8: 營業活動 | B8: 利息收入 | C8: 45747 | D8: -471390
A9: 營業活動 | B9: 股份基礎給付酬勞成本 | C9: 45747 | D9: 26842
A10: 營業活動 | B10: 採用權益法認列之關聯企業及合資利益之份額 | C10: 45747 | D10: -2657410
A11: 營業活動 | B11: 處分及報廢不動產、廠房及設備淨損失 | C11: 45747 | D11: 10151
A12: 營業活動 | B12: 處分關聯企業淨利益 | C12: 45747 | D12: -79836
A13: 營業活動 | B13: 強制透過損益按公允價值衡量之金融資產 | C13: 45747 | D13: -239746
... A53: 籌資活動 | B53: 期末現金及約當現金餘額 | C53: 45747 | D53: 29735785
